bakkeborg_xlsx_vcf-0.1.0.dist-info/METADATA
bakkeborg_xlsx_vcf-0.1.0.dist-info/WHEEL
bakkeborg_xlsx_vcf-0.1.0.dist-info/entry_points.txt
bakkeborg_xlsx_vcf/__init__.py
bakkeborg_xlsx_vcf/cli.py
bakkeborg_xlsx_vcf-0.1.0.dist-info/RECORD
